mtn_sms_v3/__init__.py
mtn_sms_v3/_base_client.py
mtn_sms_v3/_client.py
mtn_sms_v3/_compat.py
mtn_sms_v3/_constants.py
mtn_sms_v3/_exceptions.py
mtn_sms_v3/_files.py
mtn_sms_v3/_models.py
mtn_sms_v3/_qs.py
mtn_sms_v3/_resource.py
mtn_sms_v3/_response.py
mtn_sms_v3/_streaming.py
mtn_sms_v3/_types.py
mtn_sms_v3/_version.py
mtn_sms_v3/py.typed
mtn_sms_v3/_utils/__init__.py
mtn_sms_v3/_utils/_logs.py
mtn_sms_v3/_utils/_proxy.py
mtn_sms_v3/_utils/_reflection.py
mtn_sms_v3/_utils/_streams.py
mtn_sms_v3/_utils/_sync.py
mtn_sms_v3/_utils/_transform.py
mtn_sms_v3/_utils/_typing.py
mtn_sms_v3/_utils/_utils.py
mtn_sms_v3/lib/.keep
mtn_sms_v3/resources/__init__.py
mtn_sms_v3/resources/messages/__init__.py
mtn_sms_v3/resources/messages/messages.py
mtn_sms_v3/resources/messages/sms/__init__.py
mtn_sms_v3/resources/messages/sms/sms.py
mtn_sms_v3/resources/messages/sms/subscription.py
mtn_sms_v3/types/__init__.py
mtn_sms_v3/types/messages/__init__.py
mtn_sms_v3/types/messages/resource_reference.py
mtn_sms_v3/types/messages/sms_outbound_params.py
mtn_sms_v3/types/messages/sms/__init__.py
mtn_sms_v3/types/messages/sms/subscription_create_params.py
mtn_sms_v3/types/messages/sms/subscription_delete_response.py
mtn_sms_v3/types/messages/sms/subscription_response.py
mtn_sms_v3/types/messages/sms/subscription_update_params.py
mtn_sms_v3-0.0.1a1.dist-info/METADATA
mtn_sms_v3-0.0.1a1.dist-info/WHEEL
mtn_sms_v3-0.0.1a1.dist-info/licenses/LICENSE
mtn_sms_v3-0.0.1a1.dist-info/RECORD
